diskannpy/py.typed
diskannpy/module.cpp
diskannpy/dynamic_memory_index.cpp
diskannpy/_dynamic_memory_index.py
diskannpy/static_disk_index.cpp
diskannpy/_diskannpy.cpython-39-x86_64-linux-gnu.so
diskannpy/_builder.pyi
diskannpy/_builder.py
diskannpy/_static_disk_index.py
diskannpy/_static_memory_index.py
diskannpy/_common.py
diskannpy/static_memory_index.cpp
diskannpy/defaults.py
diskannpy/__init__.py
diskannpy/builder.cpp
diskannpy/_files.py
diskannpy/diskannpy.egg-info/PKG-INFO
diskannpy/diskannpy.egg-info/SOURCES.txt
diskannpy/diskannpy.egg-info/dependency_links.txt
diskannpy/diskannpy.egg-info/not-zip-safe
diskannpy/diskannpy.egg-info/top_level.txt
diskannpy/diskannpy.egg-info/requires.txt
diskannpy-0.7.0.dist-info/WHEEL
diskannpy-0.7.0.dist-info/METADATA
diskannpy-0.7.0.dist-info/top_level.txt
diskannpy-0.7.0.dist-info/LICENSE
diskannpy-0.7.0.dist-info/NOTICE.txt
diskannpy-0.7.0.dist-info/RECORD
diskannpy.libs/libmkl_def-c5f22b52.so
diskannpy.libs/libiomp5-3994699c.so
diskannpy.libs/libgomp-a97153a2.so.1.0.0
diskannpy.libs/libaio-8c118d5e.so.1.0.1
