Metadata-Version: 2.1
Name: diskannpy
Version: 0.7.0
Summary: DiskANN Python extension module
Author-email: Harsha Vardhan Simhadri <harshasi@microsoft.com>, Dax Pryce <daxpryce@microsoft.com>
License: MIT License
Requires-Python: >=3.9
License-File: LICENSE
Requires-Dist: numpy (==1.25)
Provides-Extra: dev
Requires-Dist: black ; extra == 'dev'
Requires-Dist: isort ; extra == 'dev'
Requires-Dist: mypy ; extra == 'dev'
